pfn_ase_extras/__init__.py
pfn_ase_extras/py.typed
pfn_ase_extras/genetic_operations/__init__.py
pfn_ase_extras/genetic_operations/_permutation_mutation_allow_single_element.py
pfn_ase_extras/genetic_operations/_random_composition_mutation_allow_single_element.py
pfn_ase_extras/genetic_operations/_variable_cut_and_splice_paring.py
pfn_ase_extras-0.2.2.dist-info/licenses/COPYING
pfn_ase_extras-0.2.2.dist-info/licenses/COPYING.LESSER
pfn_ase_extras-0.2.2.dist-info/licenses/LICENSE
pfn_ase_extras-0.2.2.dist-info/METADATA
pfn_ase_extras-0.2.2.dist-info/WHEEL
pfn_ase_extras-0.2.2.dist-info/top_level.txt
pfn_ase_extras-0.2.2.dist-info/RECORD
